{
  "name": "blocktrail-sdk-nodejs",
  "homepage": "https://github.com/blocktrail/blocktrail-sdk-nodejs",
  "authors": [
    "Ruben de Vries <ruben@rubensayshi.com>"
  ],
  "description": "BlockTrail's Developer Friendly API binding for NodeJS",
  "main": "main.js",
  "license": "MIT",
  "ignore": [
    "**/.*",
    "node_modules",
    "bower_components",
    "test",
    "tests"
  ],
  "version": "3.7.5",
  "_release": "3.7.5",
  "_resolution": {
    "type": "version",
    "tag": "v3.7.5",
    "commit": "55a4bccf9ad2a665f9c5acfa962c96f79620e88b"
  },
  "_source": "https://github.com/blocktrail/blocktrail-sdk-nodejs.git",
  "_target": "3.7.5",
  "_originalSource": "blocktrail-sdk"
}